celus_nigiri/__init__.py
celus_nigiri/celus.py
celus_nigiri/client.py
celus_nigiri/counter4.py
celus_nigiri/counter5.py
celus_nigiri/counter51.py
celus_nigiri/csv_detect/__init__.py
celus_nigiri/csv_detect/__main__.py
celus_nigiri/download/__init__.py
celus_nigiri/download/__main__.py
celus_nigiri/error_codes.py
celus_nigiri/exceptions.py
celus_nigiri/record.py
celus_nigiri/utils.py
celus_nigiri-5.0.1.dist-info/WHEEL
celus_nigiri-5.0.1.dist-info/entry_points.txt
celus_nigiri-5.0.1.dist-info/METADATA
celus_nigiri-5.0.1.dist-info/RECORD
