Metadata-Version: 2.4
Name: celus-nigiri
Version: 5.0.1
Summary: Library for downloading and parsing counter-like data.
Author: Beda Kosata, Stepan Henek
Author-email: Beda Kosata <beda@bigdigdata.com>, Stepan Henek <stepan@bigdigdata.com>
License-Expression: MIT
Classifier: Programming Language :: Python :: 3
Classifier: Topic :: Software Development :: Libraries
Requires-Dist: chardet>=5.0.0,<6
Requires-Dist: ijson~=3.4.0
Requires-Dist: celus-pycounter~=5.0.0
Requires-Dist: python-decouple~=3.6
Requires-Dist: python-dateutil~=2.9
Requires-Dist: xmltodict~=0.13.0
Requires-Python: >=3.12, <4
